adorad/README.md
adorad/__init__.py
adorad/_base.py
adorad/_internal.py
adorad/_meta.py
adorad/core.py
adorad/globals.py
adorad/preprocess.py
adorad/setup.py
adorad/tensor.py
adorad/visualizations.py
adorad/augment/__init__.py
adorad/augment/augments.py
adorad/color/__init__.py
adorad/color/bgr.py
adorad/color/constants.py
adorad/color/gray.py
adorad/color/hls.py
adorad/color/hsv.py
adorad/color/lab.py
adorad/color/rgb.py
adorad/data/README.md
adorad/data/__init__.py
adorad/data/audio_mixer.jpg
adorad/data/bear.jpg
adorad/data/beverages.jpg
adorad/data/black_cat.jpg
adorad/data/blue_tang.jpg
adorad/data/camera.jpg
adorad/data/controller.jpg
adorad/data/drone.jpg
adorad/data/dusk.jpg
adorad/data/fighter_fish.jpg
adorad/data/gold_fish.jpg
adorad/data/green_controller.jpg
adorad/data/green_fish.jpg
adorad/data/guitar.jpg
adorad/data/island.jpg
adorad/data/jellyfish.jpg
adorad/data/laptop.jpg
adorad/data/mountain.jpg
adorad/data/night.jpg
adorad/data/puppies.jpg
adorad/data/puppy.jpg
adorad/data/red_fish.jpg
adorad/data/rotary_phone.jpg
adorad/data/sea_turtle.jpg
adorad/data/setup.py
adorad/data/snow.jpg
adorad/data/snowflake.jpg
adorad/data/sunrise.jpg
adorad/data/tent.jpg
adorad/data/__pycache__/__init__.cpython-38.pyc
adorad/distance/__init__.py
adorad/distance/distance.py
adorad/filters/__init__.py
adorad/filters/convolve.py
adorad/filters/edges.py
adorad/filters/filter.py
adorad/filters/filters.py
adorad/io/__init__.py
adorad/io/io.py
adorad/io/resize.py
adorad/jit/__init__.py
adorad/jit/_jit_internal.py
adorad/jit/annotations.py
adorad/morph/__init__.py
adorad/morph/morph.py
adorad/ndi/__init__.py
adorad/ndi/cndsupport.py
adorad/ndi/filters.py
adorad/ndi/fourier.py
adorad/ndi/include/README.md
adorad/path/README.md
adorad/path/__init__.py
adorad/path/paths.py
adorad/path/setup.py
adorad/preprocessing/README.md
adorad/preprocessing/__init__.py
adorad/preprocessing/mean_subtraction.py
adorad/preprocessing/setup.py
adorad/segmentation/__init__.py
adorad-1.0.0.dist-info/METADATA
adorad-1.0.0.dist-info/WHEEL
adorad-1.0.0.dist-info/top_level.txt
adorad-1.0.0.dist-info/RECORD
