Metadata-Version: 2.1
Name: adorad
Version: 1.0.0
Summary: A lightweight Computer Vision library for high-performance AI research - Modern Computer Vision on the Fly.
Home-page: https://github.com/jasmcaus/adorad
Author: Jason Dsouza
Author-email: jasmcaus@gmail.com
Maintainer: Jason Dsouza
License: MIT License
Download-URL: https://pypi.org/project/adorad
Project-URL: Bug Tracker, https://github.com/jasmcaus/adorad/issues
Project-URL: Documentation, https://adorad.readthedocs.io/
Project-URL: Funding, https://www.paypal.me/jasmcaus
Project-URL: Source Code, https://github.com/jasmcaus/adorad
Keywords: adorad,computer vision,toolkit,deep learning,image processing,video processing,video stablization,video streaming,machine learning,gpu,artificial intelligence,data science,machine vision,opencv,multithreading,FFMpeg
Platform: Any
Classifier: Development Status :: 4 - Beta
Classifier: Intended Audience :: Developers
Classifier: Intended Audience :: Education
Classifier: Intended Audience :: Science/Research
Classifier: Programming Language :: Python :: 3
Classifier: Programming Language :: Python :: 3 :: Only
Classifier: Programming Language :: Python :: 3.6
Classifier: Programming Language :: Python :: 3.7
Classifier: Programming Language :: Python :: 3.8
Classifier: Operating System :: Microsoft :: Windows
Classifier: Operating System :: MacOS
Classifier: Operating System :: POSIX
Classifier: Operating System :: Unix
Classifier: Topic :: Scientific/Engineering
Classifier: Topic :: Scientific/Engineering :: Mathematics
Classifier: Topic :: Scientific/Engineering :: Artificial Intelligence
Classifier: Topic :: Scientific/Engineering :: Image Recognition
Classifier: Topic :: Scientific/Engineering :: Information Analysis
Classifier: License :: OSI Approved :: MIT License
Requires-Python: >=3.6
Requires-Dist: numpy
Requires-Dist: opencv-contrib-python
